egkdvr/__init__.py
egkdvr/plot.py
egkdvr-0.1.4.dist-info/LICENSE
egkdvr-0.1.4.dist-info/METADATA
egkdvr-0.1.4.dist-info/WHEEL
egkdvr-0.1.4.dist-info/top_level.txt
egkdvr-0.1.4.dist-info/RECORD
