Metadata-Version: 2.1
Name: egkdvr
Version: 0.1.4
Summary: Package for homework assignment
Home-page: https://pypi.org/project/egkdvr/
Author: Stanislav Tebloev
Author-email: stas.tebloev@yandex.ru
License: MIT License
Platform: UNKNOWN
Classifier: Development Status :: 1 - Planning
Classifier: License :: OSI Approved :: MIT License
Classifier: Operating System :: OS Independent
Classifier: Programming Language :: Python :: 3
Classifier: Programming Language :: Python :: 3 :: Only
Classifier: Programming Language :: Python :: 3.7
Classifier: Programming Language :: Python :: 3.8
Classifier: Programming Language :: Python :: 3.9
Requires-Dist: matplotlib (<3.1.3)
